{
	"0" : "౦",
	"1" : "౧",
	"2" : "౨",
	"3" : "౩",
	"4" : "౪",
	"5" : "౫",
	"6" : "౬",
	"7" : "౭",
	"8" : "౮",
	"9" : "౯",
	"00" : "0",
	"11" : "1",
	"22" : "2",
	"33" : "3",
	"44" : "4",
	"55" : "5",
	"66" : "6",
	"77" : "7",
	"88" : "8",
	"99" : "9",
	"a" : "ా",
	"aa" : "అ",
	"aaa" : "ఆ",
	"A" : "అ",
	"AA" : "ఆ",
	"b" : "బ",
	"bb" : "భ",
	"B" : "భ",
	"c" : "చ",
	"cc" : "ఛ",
	"ccc" : "క్ష",
	"C" : "ఛ",
	"CC" : "క్ష",
	"d" : "ద",
	"dd" : "ధ",
	"ddd" : "డ",
	"dddd" : "ఢ",
	"ddddd" : "ౘ",
	"dddddd" : "ద్ధ",
	"ddddddd" : "ద్వ",
	"dddddddd" : "ద్య",
	"ddddddddd" : "ద్ద",
	"dddddddddd" : "ద్న",
	"D" : "డ",
	"DD" : "ఢ",
	"DDD" : "ౘ",
	"e" : "ె",
	"ee" : "ే",
	"eee" : "ై",
	"eeee" : "ఎ",
	"eeeee" : "ఏ",
	"eeeeee" : "ఐ",
	"eeeeeee" : "ౖ",
	"E" : "ఎ",
	"EE" : "ఏ",
	"EEE" : "ఐ",
	"f" : "ఫ",
	"F" : "ఫ",
	"g" : "గ",
	"gg" : "ఘ",
	"ggg" : "ఙ",
	"gggg" : "జ్ఞ",
	"G" : "ఘ",
	"GG" : "ఙ",
	"h" : "హ",
	"hh" : "హ్మ",
	"hhh" : "హ్య",
	"hhhh" : "హ్ల",
	"hhhhh" : "హ్న",
	"hhhhhh" : "హ్వ",
	"H" : "హ",
	"i" : "ి",
	"ii" : "ీ",
	"iii" : "ఇ",
	"iiii" : "ఈ",
	"I" : "ఇ",
	"II" : "ఈ",
	"j" : "జ",
	"jj" : "ఝ",
	"jjj" : "ఞ",
	"jjjj" : "జ్ఞ",
	"J" : "ఝ",
	"JJ" : "ఞ",
	"k" : "క",
	"kk" : "ఖ",
	"kkk" : "క్త",
	"K" : "ఖ",
	"l" : "ల",
	"ll" : "ళ",
	"lll" : "ౢ",
	"llll" : "ౣ",
	"lllll" : "ఌ",
	"llllll" : "ౡ",
	"L" : "ళ",
	"LL" : "ఌ",
	"LLL" : "ౡ",
	"m" : "మ",
	"M" : "మ",
	"n" : "న",
	"nn" : "ణ",
	"N" : "ణ",
	"o" : "ొ",
	"oo" : "ో",
	"ooo" : "ౌ",
	"oooo" : "ఒ",
	"ooooo" : "ఓ",
	"oooooo" : "ఔ",
	"O" : "ఒ",
	"OO" : "ఓ",
	"OOO" : "ఔ",
	"p" : "ప",
	"pp" : "ఫ",
	"P" : "ప",
	"q" : "‍",
	"qq" : "‌",
	"r" : "ర",
	"rr" : "్ర",
	"rrr" : "ృ",
	"rrrr" : "ర్",
	"rrrrr" : "ఱ",
	"rrrrrr" : "ఱ్",
	"rrrrrrr" : "ౄ",
	"rrrrrrrr" : "ఋ",
	"rrrrrrrrr" : "ౠ",
	"R" : "ఋ",
	"RR" : "ౠ",
	"s" : "స",
	"ss" : "శ",
	"sss" : "ష",
	"ssss" : "శ్ర",
	"S" : "శ",
	"SS" : "ష",
	"SSS" : "శ్ర",
	"t" : "త",
	"tt" : "థ",
	"ttt" : "ట",
	"tttt" : "ఠ",
	"ttttt" : "త్ర",
	"tttttt" : "ౙ",
	"T" : "ట",
	"TT" : "ఠ",
	"TTT" : "త్ర",
	"TTTT" : "ౙ",
	"u" : "ు",
	"uu" : "ూ",
	"uuu" : "ఉ",
	"uuuu" : "ఊ",
	"U" : "ఉ",
	"UU" : "ఊ",
	"v" : "వ",
	"V" : "వ",
	"w" : "వ",
	"W" : "వ",
	"x" : "్",
	"X" : "్",
	"y" : "య",
	"yy" : "ఞ",
	"Y" : "ఞ",
	"z" : "ఁ",
	"zz" : "ం",
	"zzz" : "ః",
	"zzzz" : "ౕ",
	"zzzzz" : "ఽ",
	"Z" : "ఽ"
}