{
	"0" : "൦",
	"1" : "൧",
	"2" : "൨",
	"3" : "൩",
	"4" : "൪",
	"5" : "൫",
	"6" : "൬",
	"7" : "൭",
	"8" : "൮",
	"9" : "൯",
	"00" : "0",
	"11" : "1",
	"22" : "2",
	"33" : "3",
	"44" : "4",
	"55" : "5",
	"66" : "6",
	"77" : "7",
	"88" : "8",
	"99" : "9",	
	"a" : "ാ",
	"aa" : "അ",
	"aaa" : "ആ",
	"A" : "അ",
	"AA" : "ആ",
	"b" : "ബ",
	"bb" : "ഭ",
	"B" : "ഭ",
	"c" : "ച",
	"cc" : "ഛ",
	"ccc" : "ക്ഷ",
	"C" : "ഛ",
	"CC" : "ക്ഷ",
	"d" : "ദ",
	"dd" : "ധ",
	"ddd" : "ഡ",
	"dddd" : "ഢ",
	"ddddd" : "ദ്ധ",
	"dddddd" : "ദ്വ",
	"ddddddd" : "ദ്യ",
	"dddddddd" : "ദ്ദ",
	"ddddddddd" : "ദ്ന",
	"dddddddddd" : "ദ്മ",
	"D" : "ഡ",
	"DD" : "ഢ",
	"e" : "െ",
	"ee" : "േ",
	"eee" : "ൈ",
	"eeee" : "എ",
	"eeeee" : "ഏ",
	"eeeeee" : "ഐ",
	"E" : "എ",
	"EE" : "ഏ",
	"EEE" : "ഐ",
	"f" : "ഫ",
	"g" : "ഗ",
	"gg" : "ഘ",
	"ggg" : "ങ",
	"G" : "ങ",
	"h" : "ഹ",
	"hh" : "ഹ്മ",
	"hhh" : "ഹ്യ",
	"hhhh" : "ഹ്ല",
	"hhhhh" : "ഹ്ന",
	"hhhhhh" : "ഹ്വ",
	"i" : "ി",
	"ii" : "ീ",
	"iii" : "ഇ",
	"iiii" : "ഈ",
	"I" : "ഇ",
	"II" : "ഈ",	
	"j" : "ജ",
	"jj" : "ഝ",
	"jjj" : "ജ്ഞ",
	"jjjj" : "ഞ",
	"jjjjj" : "ഴ",
	"J" : "ഴ",
	"JJ" : "ഞ",
	"k" : "ക",
	"kk" : "ഖ",
	"kkk" : "ൿ",
	"kkkk" : "ക്ത",
	"K" : "ൿ",
	"l" : "ല",
	"ll" : "ള",
	"lll" : "ല്‍",
	"llll" : "ള്‍",
	"lllll" : "‍ൢ",
	"llllll" : "ൣ‍",
	"lllllll" : "ഌ",
	"llllllll" : "ൡ",
	"L" : "ല്‍",
	"LL" : "ള്‍",
	"LLL" : "ഌ‍",
	"LLLL" : "ൡ‍",
	"m" : "മ",
	"n" : "ന",
	"nn" : "ണ",
	"nnn" : "ന്‍",
	"nnnn" : "ണ്‍",
	"N" : "ന്‍",
	"NN" : "ണ്‍",
	"o" : "ൊ",
	"oo" : "ോ",
	"ooo" : "ൌ",
	"oooo" : "ഒ",
	"ooooo" : "ഓ",
	"oooooo" : "ഔ",
	"ooooooo" : "ൗ",
	"O" : "ഒ",
	"OO" : "ഓ",
	"OOO" : "ഔ",
	"p" : "പ",
	"pp" : "ഫ",
	"q" : "‍",
	"qq" : "‌",
	"r" : "ര",
	"rr" : "്ര",
	"rrr" : "ൃ",
	"rrrr" : "ൄ",
	"rrrrr" : "ര്",
	"rrrrrr" : "റ",
	"rrrrrrr" : "റ്‍",
	"rrrrrrrr" : "ര്‍",
	"rrrrrrrrr" : "ഋ",
	"rrrrrrrrrr" : "ൠ",
	"R" : "റ‍",
	"RR" : "ര്‍",
	"RRR" : "ഋ",
	"RRRR" : "ൠ",
	"s" : "സ",
	"ss" : "ശ",
	"sss" : "ഷ",
	"ssss" : "ശ്ര",
	"S" : "ശ",
	"SS" : "ഷ",
	"SSS" : "ശ്ര",
	"t" : "ത",
	"tt" : "ഥ",
	"ttt" : "ട",
	"tttt" : "ഠ",
	"ttttt" : "ത്ര",
	"T" : "ട",
	"TT" : "ഠ",
	"TTT" : "ത്ര",
	"u" : "ു",
	"uu" : "ൂ",
	"uuu" : "ഉ",
	"uuuu" : "ഊ",
	"U" : "ഉ",
	"UU" : "ഊ",
	"v" : "വ",
	"w" : "വ",
	"x" : "്",
	"y" : "യ",
	"yy" : "ഞ",
	"z" : "ം",
	"zz" : "ഃ",
	"zzz" : "ഴ",
	"zzzz" : "ഽ",
	"Z" : "ഽ"
}